xp_xscreensaver/__init__.py
xp_xscreensaver/logon.png
xp_xscreensaver-0.1.dist-info/METADATA
xp_xscreensaver-0.1.dist-info/RECORD
xp_xscreensaver-0.1.dist-info/WHEEL
xp_xscreensaver-0.1.dist-info/entry_points.txt
xp_xscreensaver-0.1.dist-info/top_level.txt
