Metadata-Version: 2.1
Name: xp-xscreensaver
Version: 0.1
Summary: XP logon screensaver for xscreensaver
Home-page: https://github.com/theblazehen/xp_xscreensaver
Author: Jeandre Le Roux
Author-email: theblazehen@theblazehen.com
License: MIT
Platform: UNKNOWN
